{
    "active_listings": "80",
    "active_listings_up_down": "up",
    "analytics_uri": "https://www.realtor.com/realestateandhomes-search/90255",
    "average_days_on_market": "57",
    "average_days_on_market_up_down": "down",
    "description": "Huntington Park",
    "extract_day_id": "20210419",
    "extract_dt": "04/19/2021, 10:57:43",
    "median_list_price": "584,162",
    "median_list_price_up_down": "up",
    "median_price_per_sqft": "347",
    "median_price_per_sqft_up_down": "down",
    "price_reduced_status": "https://www.redfin.com/zipcode/90255/filter/max-price-reduced=1d",
    "price_reduced_today": 0,
    "search_uri": "https://www.redfin.com/zipcode/90255",
    "zipcode": "90255"
}